setup.cfg
setup.py
imgurpython/__init__.py
imgurpython/client.py
imgurpython/main.py
imgurpython.egg-info/PKG-INFO
imgurpython.egg-info/SOURCES.txt
imgurpython.egg-info/dependency_links.txt
imgurpython.egg-info/requires.txt
imgurpython.egg-info/top_level.txt
imgurpython/data/config.json.sample
imgurpython/data/res/corgi.jpg
imgurpython/data/res/error.jpg
imgurpython/helpers/__init__.py
imgurpython/helpers/error.py
imgurpython/helpers/format.py
imgurpython/imgur/__init__.py
imgurpython/imgur/factory.py
imgurpython/imgur/imgur.py
imgurpython/imgur/ratelimit.py
imgurpython/imgur/auth/__init__.py
imgurpython/imgur/auth/accesstoken.py
imgurpython/imgur/auth/anonymous.py
imgurpython/imgur/auth/base.py
imgurpython/imgur/auth/expired.py
imgurpython/imgur/models/__init__.py
imgurpython/imgur/models/account.py
imgurpython/imgur/models/account_settings.py
imgurpython/imgur/models/album.py
imgurpython/imgur/models/comment.py
imgurpython/imgur/models/conversation.py
imgurpython/imgur/models/custom_gallery.py
imgurpython/imgur/models/gallery_album.py
imgurpython/imgur/models/gallery_image.py
imgurpython/imgur/models/image.py
imgurpython/imgur/models/message.py
imgurpython/imgur/models/notification.py
imgurpython/imgur/models/tag.py
imgurpython/imgur/models/tag_vote.py